README.md
setup.cfg
setup.py
video_razor/__init__.py
video_razor/razor.py
video_razor.egg-info/PKG-INFO
video_razor.egg-info/SOURCES.txt
video_razor.egg-info/dependency_links.txt
video_razor.egg-info/requires.txt
video_razor.egg-info/top_level.txt