Metadata-Version: 2.1
Name: video-razor
Version: 0.0.3
Summary: A package for slicing a video into N sections
Home-page: https://github.com/5starkarma/video-razor
Author: David Alford
Author-email: firstlast678@gmail.com
License: MIT
Download-URL: https://github.com/5starkarma/video-razor/archive/0.0.3.tar.gz
Keywords: OPENCV,VIDEO,CUT,SLICE,RAZOR
Platform: UNKNOWN
Classifier: Development Status :: 3 - Alpha
Classifier: Intended Audience :: Developers
Classifier: Programming Language :: Python :: 3
Classifier: Programming Language :: Python :: 3.4
Classifier: Programming Language :: Python :: 3.5
Classifier: Programming Language :: Python :: 3.6
Classifier: Topic :: Software Development :: Build Tools
Classifier: License :: OSI Approved :: MIT License
Classifier: Operating System :: OS Independent
Requires-Python: >=3.6
